nonebot_plugin_systools_dev/__init__.py
nonebot_plugin_systools_dev/config.py
nonebot_plugin_systools_dev-0.1.2.dist-info/METADATA
nonebot_plugin_systools_dev-0.1.2.dist-info/WHEEL
nonebot_plugin_systools_dev-0.1.2.dist-info/top_level.txt
nonebot_plugin_systools_dev-0.1.2.dist-info/RECORD
