Metadata-Version: 2.1
Name: nonebot-plugin-systools-dev
Version: 0.1.2
Summary: 系统助手 for Nonebot - 支持运行系统命令、备份 Koishi 配置文件到 GitHub、查询系统状态、获取 IP 地址等进阶操作
Requires-Python: <4.0,>=3.8
Requires-Dist: nonebot2
Requires-Dist: nonebot-adapter-onebot
